hestia_earth/schema/__init__.py
hestia_earth/schema/pydantic/__init__.py
hestia_earth/schema/utils/__init__.py
hestia_earth/schema/utils/sort.py
hestia_earth_schema-35.4.2.dist-info/licenses/LICENSE
hestia_earth_schema-35.4.2.dist-info/METADATA
hestia_earth_schema-35.4.2.dist-info/WHEEL
hestia_earth_schema-35.4.2.dist-info/top_level.txt
hestia_earth_schema-35.4.2.dist-info/RECORD
