Metadata-Version: 2.4
Name: hestia_earth_schema
Version: 35.4.2
Summary: HESTIA Schema library
Home-page: https://gitlab.com/hestia-earth/hestia-schema
Author: Guillaume Royer
Author-email: guillaumeroyer.mail@gmail.com
License: MIT
Keywords: hestia,schema
Requires-Python: >=3.12
License-File: LICENSE
Dynamic: author
Dynamic: author-email
Dynamic: description
Dynamic: description-content-type
Dynamic: home-page
Dynamic: keywords
Dynamic: license
Dynamic: license-file
Dynamic: requires-python
Dynamic: summary
